{
    "grid": [
        {
            "letter": "o",
            "row": 0,
            "col": 0
        },
        {
            "letter": "d",
            "row": 0,
            "col": 1
        },
        {
            "letter": "u",
            "row": 0,
            "col": 2
        },
        {
            "letter": "f",
            "row": 0,
            "col": 3
        },
        {
            "letter": "f",
            "row": 0,
            "col": 4
        },
        {
            "letter": "e",
            "row": 0,
            "col": 5
        },
        {
            "letter": "d",
            "row": 0,
            "col": 6
        },
        {
            "letter": "b",
            "row": 0,
            "col": 7
        },
        {
            "letter": "f",
            "row": 1,
            "col": 0
        },
        {
            "letter": "v",
            "row": 1,
            "col": 1
        },
        {
            "letter": "q",
            "row": 1,
            "col": 2
        },
        {
            "letter": "j",
            "row": 1,
            "col": 3
        },
        {
            "letter": "a",
            "row": 1,
            "col": 4
        },
        {
            "letter": "k",
            "row": 1,
            "col": 5
        },
        {
            "letter": "c",
            "row": 1,
            "col": 6
        },
        {
            "letter": "w",
            "row": 1,
            "col": 7
        },
        {
            "letter": "f",
            "row": 2,
            "col": 0
        },
        {
            "letter": "i",
            "row": 2,
            "col": 1
        },
        {
            "letter": "e",
            "row": 2,
            "col": 2
        },
        {
            "letter": "r",
            "row": 2,
            "col": 3
        },
        {
            "letter": "n",
            "row": 2,
            "col": 4
        },
        {
            "letter": "r",
            "row": 2,
            "col": 5
        },
        {
            "letter": "b",
            "row": 2,
            "col": 6
        },
        {
            "letter": "e",
            "row": 2,
            "col": 7
        },
        {
            "letter": "y",
            "row": 3,
            "col": 0
        },
        {
            "letter": "s",
            "row": 3,
            "col": 1
        },
        {
            "letter": "s",
            "row": 3,
            "col": 2
        },
        {
            "letter": "w",
            "row": 3,
            "col": 3
        },
        {
            "letter": "e",
            "row": 3,
            "col": 4
        },
        {
            "letter": "l",
            "row": 3,
            "col": 5
        },
        {
            "letter": "t",
            "row": 3,
            "col": 6
        },
        {
            "letter": "h",
            "row": 3,
            "col": 7
        },
        {
            "letter": "t",
            "row": 4,
            "col": 0
        },
        {
            "letter": "c",
            "row": 4,
            "col": 1
        },
        {
            "letter": "j",
            "row": 4,
            "col": 2
        },
        {
            "letter": "e",
            "row": 4,
            "col": 3
        },
        {
            "letter": "t",
            "row": 4,
            "col": 4
        },
        {
            "letter": "a",
            "row": 4,
            "col": 5
        },
        {
            "letter": "z",
            "row": 4,
            "col": 6
        },
        {
            "letter": "a",
            "row": 4,
            "col": 7
        },
        {
            "letter": "l",
            "row": 5,
            "col": 0
        },
        {
            "letter": "o",
            "row": 5,
            "col": 1
        },
        {
            "letter": "d",
            "row": 5,
            "col": 2
        },
        {
            "letter": "e",
            "row": 5,
            "col": 3
        },
        {
            "letter": "h",
            "row": 5,
            "col": 4
        },
        {
            "letter": "d",
            "row": 5,
            "col": 5
        },
        {
            "letter": "l",
            "row": 5,
            "col": 6
        },
        {
            "letter": "q",
            "row": 5,
            "col": 7
        },
        {
            "letter": "k",
            "row": 6,
            "col": 0
        },
        {
            "letter": "v",
            "row": 6,
            "col": 1
        },
        {
            "letter": "z",
            "row": 6,
            "col": 2
        },
        {
            "letter": "t",
            "row": 6,
            "col": 3
        },
        {
            "letter": "u",
            "row": 6,
            "col": 4
        },
        {
            "letter": "l",
            "row": 6,
            "col": 5
        },
        {
            "letter": "g",
            "row": 6,
            "col": 6
        },
        {
            "letter": "m",
            "row": 6,
            "col": 7
        },
        {
            "letter": "d",
            "row": 7,
            "col": 0
        },
        {
            "letter": "y",
            "row": 7,
            "col": 1
        },
        {
            "letter": "o",
            "row": 7,
            "col": 2
        },
        {
            "letter": "k",
            "row": 7,
            "col": 3
        },
        {
            "letter": "m",
            "row": 7,
            "col": 4
        },
        {
            "letter": "f",
            "row": 7,
            "col": 5
        },
        {
            "letter": "b",
            "row": 7,
            "col": 6
        },
        {
            "letter": "e",
            "row": 7,
            "col": 7
        }
    ],
    "words": [
        "overedge",
        "creeded",
        "duffed",
        "pennaria",
        "scovy",
        "realm",
        "swelth",
        "anethum"
    ]
}